[
	{
		"accountno": "0211200001",
		"address": "calampisawan",
		"arrears": "0.00",
		"averageuse": "29",
		"bill_date": "02/03/2025",
		"bill_no": "00068149",
		"c_route_no": "02-28",
		"c_statdesc": "active",
		"c_type": "1",
		"discon_dat": "02/17/2025",
		"due_date": "02/13/2025",
		"fullname": "abellon, jessica",
		"installfee": "0.0",
		"metercode": "2",
		"mrrf": "0.00",
		"mtr_no": "180405339",
		"prereading": "876",
		"prorated": "0",
		"prvmr_date": "01/06/2025",
		"reminders": "",
		"res2": "0"
	},
	{
		"accountno": "0211200002",
		"address": "calampisawan",
		"arrears": "0.00",
		"averageuse": "14",
		"bill_date": "02/03/2025",
		"bill_no": "00068150",
		"c_route_no": "02-29",
		"c_statdesc": "active",
		"c_type": "1",
		"discon_dat": "02/17/2025",
		"due_date": "02/13/2025",
		"fullname": "albarico, fernando jr/armando",
		"installfee": "0.0",
		"metercode": "2",
		"mrrf": "0.00",
		"mtr_no": "94115516",
		"prereading": "2747",
		"prorated": "0",
		"prvmr_date": "01/06/2025",
		"reminders": "",
		"res2": "0"
	},
	{
		"accountno": "0211200005",
		"address": "calampisawan",
		"arrears": "0.00",
		"averageuse": "9",
		"bill_date": "02/03/2025",
		"bill_no": "00068151",
		"c_route_no": "05-03",
		"c_statdesc": "active",
		"c_type": "1",
		"discon_dat": "02/17/2025",
		"due_date": "02/13/2025",
		"fullname": "amaro, maria gigie",
		"installfee": "0.0",
		"metercode": "2",
		"mrrf": "0.00",
		"mtr_no": "7096",
		"prereading": "2373",
		"prorated": "0",
		"prvmr_date": "01/06/2025",
		"reminders": "",
		"res2": "0"
	},
	{
		"accountno": "0211200006",
		"address": "calampisawan",
		"arrears": "0.00",
		"averageuse": "46",
		"bill_date": "02/03/2025",
		"bill_no": "00068152",
		"c_route_no": "02-17",
		"c_statdesc": "active",
		"c_type": "1",
		"discon_dat": "02/17/2025",
		"due_date": "02/13/2025",
		"fullname": "angcos, emmanuel",
		"installfee": "0.0",
		"metercode": "2",
		"mrrf": "0.00",
		"mtr_no": "120711288",
		"prereading": "3963",
		"prorated": "0",
		"prvmr_date": "01/06/2025",
		"reminders": "",
		"res2": "0"
	},
	{
		"accountno": "0211200007",
		"address": "calampisawan",
		"arrears": "798.50",
		"averageuse": "22",
		"bill_date": "02/03/2025",
		"bill_no": "00068153",
		"c_route_no": "03-12",
		"c_statdesc": "active",
		"c_type": "1",
		"discon_dat": "02/17/2025",
		"due_date": "02/13/2025",
		"fullname": "angcos, maricel",
		"installfee": "0.0",
		"metercode": "2",
		"mrrf": "35.75",
		"mtr_no": "100305893",
		"prereading": "2253",
		"prorated": "0",
		"prvmr_date": "01/06/2025",
		"reminders": "",
		"res2": "0"
	},
	{
		"accountno": "0211200008",
		"address": "calampisawan",
		"arrears": "316.50",
		"averageuse": "27",
		"bill_date": "02/03/2025",
		"bill_no": "00068154",
		"c_route_no": "04-05",
		"c_statdesc": "active",
		"c_type": "1",
		"discon_dat": "02/17/2025",
		"due_date": "02/13/2025",
		"fullname": "angcos, mariano, jr.",
		"installfee": "0.0",
		"metercode": "2",
		"mrrf": "7.25",
		"mtr_no": "180006961",
		"prereading": "882",
		"prorated": "0",
		"prvmr_date": "01/06/2025",
		"reminders": "",
		"res2": "0"
	},
	{
		"accountno": "0211200009",
		"address": "calampisawan",
		"arrears": "0.00",
		"averageuse": "2",
		"bill_date": "02/03/2025",
		"bill_no": "00068155",
		"c_route_no": "03-09",
		"c_statdesc": "active",
		"c_type": "1",
		"discon_dat": "02/17/2025",
		"due_date": "02/13/2025",
		"fullname": "angcos, virginia",
		"installfee": "0.0",
		"metercode": "2",
		"mrrf": "0.00",
		"mtr_no": "9499369",
		"prereading": "2792",
		"prorated": "0",
		"prvmr_date": "01/06/2025",
		"reminders": "",
		"res2": "0"
	}
]
